optprc/Asian.py
optprc/IRS.py
optprc/Vanilla.py
optprc/__init__.py
optprc/iData.py
optprc/iDate.py
optprc/iMath.py
eHyena-0.0.2.dist-info/LICENSE
eHyena-0.0.2.dist-info/METADATA
eHyena-0.0.2.dist-info/WHEEL
eHyena-0.0.2.dist-info/top_level.txt
eHyena-0.0.2.dist-info/RECORD
