Metadata-Version: 2.1
Name: eHyena
Version: 0.0.2
Summary: option pricer
Home-page: https://www.optprc.com
Author: Julian Gong
Author-email: juliangong@hotmail.com
License: UNKNOWN
Platform: UNKNOWN
Classifier: Programming Language :: Python :: 2.7
Classifier: Programming Language :: Python :: 3
Classifier: License :: OSI Approved :: MIT License
Classifier: Operating System :: OS Independent
